LICENSE
MANIFEST.in
README.rst
setup.cfg
setup.py
versioneer.py
scikit_surgerybard.egg-info/PKG-INFO
scikit_surgerybard.egg-info/SOURCES.txt
scikit_surgerybard.egg-info/dependency_links.txt
scikit_surgerybard.egg-info/entry_points.txt
scikit_surgerybard.egg-info/requires.txt
scikit_surgerybard.egg-info/top_level.txt
sksurgerybard/__init__.py
sksurgerybard/_version.py
sksurgerybard/algorithms/__init__.py
sksurgerybard/algorithms/bard_config_algorithms.py
sksurgerybard/algorithms/bard_config_speech.py
sksurgerybard/algorithms/decimation.py
sksurgerybard/algorithms/pointer.py
sksurgerybard/interaction/__init__.py
sksurgerybard/interaction/interaction.py
sksurgerybard/interaction/speech_interaction.py
sksurgerybard/tracking/__init__.py
sksurgerybard/tracking/bard_tracking.py
sksurgerybard/ui/__init__.py
sksurgerybard/ui/bard_procrustes_app.py
sksurgerybard/ui/bard_procrustes_command_line.py
sksurgerybard/ui/sksurgerybard_command_app.py
sksurgerybard/ui/sksurgerybard_command_line.py
sksurgerybard/visualisation/__init__.py
sksurgerybard/visualisation/bard_visualisation.py
sksurgerybard/widgets/__init__.py
sksurgerybard/widgets/bard_overlay_app.py
tests/test_requirements.py
tests/algorithms/__init__.py
tests/algorithms/test_configure_bard.py
tests/algorithms/test_decimation.py
tests/algorithms/test_pointer.py
tests/interaction/__init__.py
tests/interaction/test_interaction.py
tests/interaction/test_speech_interation.py
tests/tracking/__init__.py
tests/tracking/test_tracking.py
tests/visualisation/__init__.py
tests/visualisation/test_visualisation.py
tests/widgets/__init__.py
tests/widgets/test_bard_overlay.py